moteur_server_rest/auth.py
moteur_server_rest/bootstrap.py
moteur_server_rest/config.py
moteur_server_rest/file_utils.py
moteur_server_rest/jvm_utils.py
moteur_server_rest/routes.py
moteur_server_rest/server.py
moteur_server_rest/workflow_manager.py
moteur_server_rest/wsgi.py
moteur_server_rest-0.2.2.dist-info/METADATA
moteur_server_rest-0.2.2.dist-info/WHEEL
moteur_server_rest-0.2.2.dist-info/RECORD
