Metadata-Version: 2.4
Name: moteur-server-rest
Version: 0.2.2
Author-email: Hippolyte Blot <hippolyte.blot@creatis.insa-lyon.fr>, Axel Bonnet <axel.bonnet@creatis.insa-lyon.fr>
Requires-Python: >=3.9
Requires-Dist: flask-httpauth<5.0,>=4.8
Requires-Dist: flask<4.0,>=3.0
Requires-Dist: gunicorn>=23.0.0
Requires-Dist: psutil<7,>=6
Requires-Dist: python-dotenv<2.0,>=1.0
Requires-Dist: requests<3.0,>=2.32
